constellaxion/__init__.py
constellaxion/main.py
constellaxion/utils.py
constellaxion/commands/__init__.py
constellaxion/commands/init.py
constellaxion/commands/login.py
constellaxion/commands/model.py
constellaxion/handlers/__init__.py
constellaxion/handlers/cloud_job.py
constellaxion/handlers/dataset.py
constellaxion/handlers/model.py
constellaxion/handlers/training.py
constellaxion/models/__init__.py
constellaxion/models/model_map.py
constellaxion/models/scripts/aws/__init__.py
constellaxion/models/scripts/gcp/__init__.py
constellaxion/models/scripts/gcp/lora.py
constellaxion/services/__init__.py
constellaxion/services/aws/__init__.py
constellaxion/services/aws/aws_deploy_job.py
constellaxion/services/aws/iam.py
constellaxion/services/aws/prompt_aws_model.py
constellaxion/services/aws/utils.py
constellaxion/services/gcp/__init__.py
constellaxion/services/gcp/gcp_cloud_run.py
constellaxion/services/gcp/gcp_deploy_job.py
constellaxion/services/gcp/iam.py
constellaxion/services/gcp/prompt_gcp_model.py
constellaxion/services/gcp/serve_job.py
constellaxion/services/gcp/storage.py
constellaxion/services/gcp/train_job.py
constellaxion/types/__init__.py
constellaxion/ui/prompts/404.html
constellaxion/ui/prompts/favicon.ico
constellaxion/ui/prompts/file.svg
constellaxion/ui/prompts/globe.svg
constellaxion/ui/prompts/index.html
constellaxion/ui/prompts/index.txt
constellaxion/ui/prompts/logo_prompt_ui_dark_bg.svg
constellaxion/ui/prompts/logo_prompt_ui_light_bg.svg
constellaxion/ui/prompts/logo_x.png
constellaxion/ui/prompts/next.svg
constellaxion/ui/prompts/vercel.svg
constellaxion/ui/prompts/window.svg
constellaxion/ui/prompts/404/index.html
constellaxion/ui/prompts/_next/static/chunks/242-3b39d324338c9334.js
constellaxion/ui/prompts/_next/static/chunks/4bd1b696-79caff0c960666f8.js
constellaxion/ui/prompts/_next/static/chunks/684-3026217af8a1b6a9.js
constellaxion/ui/prompts/_next/static/chunks/9c4e2130-a077bf4fcac0ae95.js
constellaxion-0.4.3.dist-info/METADATA
constellaxion-0.4.3.dist-info/WHEEL
constellaxion-0.4.3.dist-info/entry_points.txt
constellaxion-0.4.3.dist-info/top_level.txt
constellaxion-0.4.3.dist-info/RECORD
