Metadata-Version: 2.1
Name: constellaxion
Version: 0.4.3
Summary: The constellaXion CLI for managing your laboratory database
Author: Constellaxion Technologies, Inc.
Author-email: dev@constellaxion.ai
Keywords: constellaxion,ai,ml ops
Classifier: Programming Language :: Python :: 3
Classifier: License :: OSI Approved :: MIT License
Classifier: Operating System :: OS Independent
Requires-Python: >=3.10
Requires-Dist: requests
Requires-Dist: rich
Requires-Dist: google-cloud-aiplatform
Requires-Dist: google-api-python-client
Requires-Dist: google-cloud-run
Requires-Dist: pyfiglet
Requires-Dist: halo
Requires-Dist: pydantic
Requires-Dist: pyyaml
Requires-Dist: click
Requires-Dist: boto3
Requires-Dist: sagemaker
Requires-Dist: pynput
Requires-Dist: tabulate
Requires-Dist: protobuf==3.20.3
